IDEA_SESIT/__init__.py
IDEA_SESIT/PythonAnywhere_website/__init__.py
IDEA_SESIT/PythonAnywhere_website/app.py
IDEA_SESIT/copper/__init__.py
IDEA_SESIT/copper/copper_data_summary.py
IDEA_SESIT/copper/copper_extension.py
IDEA_SESIT/copper/copper_results.py
IDEA_SESIT/copper/plot_installed_capacity.py
IDEA_SESIT/main/Combined_Visualization_Current.py
IDEA_SESIT/main/__init__.py
IDEA_SESIT/main/OSeMOSYS/OSeMOSYS.py
IDEA_SESIT/main/OSeMOSYS/__init__.py
IDEA_SESIT/main/OSeMOSYS/format_data.py
IDEA_SESIT/main/Panel_app/Combined_Visualization.py
IDEA_SESIT/main/Panel_app/__init__.py
IDEA_SESIT/postprocess_scripts/COPPER_Data_analyze_v4.py
IDEA_SESIT/postprocess_scripts/__init__.py
IDEA_SESIT/postprocess_scripts/SILVER_postprocess/SILVER_Post_Process_app.py
IDEA_SESIT/postprocess_scripts/SILVER_postprocess/__init__.py
IDEA_SESIT/postprocess_scripts/SILVER_postprocess/query_SILVER.py
IDEA_SESIT-0.0.11.dist-info/LICENSE
IDEA_SESIT-0.0.11.dist-info/METADATA
IDEA_SESIT-0.0.11.dist-info/WHEEL
IDEA_SESIT-0.0.11.dist-info/top_level.txt
IDEA_SESIT-0.0.11.dist-info/RECORD
